<?xml version="1.0" encoding="UTF-8"?>
<!DOCTYPE mapper PUBLIC "-//mybatis.org//DTD Mapper 3.0//EN" "http://mybatis.org/dtd/mybatis-3-mapper.dtd">

<mapper namespace="com.jiudian.modules.cms.dao.NcCmsArticleDao">

	<!-- 可根据自己的需求，是否要使用 -->
    <resultMap type="com.jiudian.modules.cms.entity.NcCmsArticleEntity" id="ncCmsArticleMap">
        <result property="articleId" column="article_id"/>
        <result property="title" column="title"/>
        <result property="classId" column="class_id"/>
        <result property="shortTitle" column="short_title"/>
        <result property="source" column="source"/>
        <result property="url" column="url"/>
        <result property="author" column="author"/>
        <result property="summary" column="summary"/>
        <result property="content" column="content"/>
        <result property="image" column="image"/>
        <result property="keyword" column="keyword"/>
        <result property="articleIdArray" column="article_id_array"/>
        <result property="click" column="click"/>
        <result property="sort" column="sort"/>
        <result property="commendFlag" column="commend_flag"/>
        <result property="commentFlag" column="comment_flag"/>
        <result property="status" column="status"/>
        <result property="attachmentPath" column="attachment_path"/>
        <result property="tag" column="tag"/>
        <result property="commentCount" column="comment_count"/>
        <result property="shareCount" column="share_count"/>
        <result property="publisherName" column="publisher_name"/>
        <result property="uid" column="uid"/>
        <result property="lastCommentTime" column="last_comment_time"/>
        <result property="publicTime" column="public_time"/>
        <result property="createTime" column="create_time"/>
        <result property="modifyTime" column="modify_time"/>
    </resultMap>


</mapper>